LICENCE
MANIFEST.in
README.md
fig1.png
fig2.png
fig3.png
setup.py
souwapy/SOUWA.py
souwapy/__init__.py
souwapy.egg-info/PKG-INFO
souwapy.egg-info/SOURCES.txt
souwapy.egg-info/dependency_links.txt
souwapy.egg-info/top_level.txt
tests/__init__.py
tests/test_souwa.py