Metadata-Version: 1.1
Name: souwapy
Version: 1.1.1
Summary: This is a library for summing array elements with high speed by new algorithm.
Home-page: https://github.com/tanaikech/souwapy
Author: Kanshi TANAIKE
Author-email: tanaike@hotmail.com
License: MIT License
Keywords: array,sum,speed,algorithm,pyramid,new algorithm
Platform: UNKNOWN
Classifier: Development Status :: 5 - Production/Stable
Classifier: Intended Audience :: Developers
Classifier: Intended Audience :: Science/Research
Classifier: License :: OSI Approved :: MIT License
Classifier: Natural Language :: English
Classifier: Programming Language :: Python :: 2.7
Classifier: Programming Language :: Python :: 3.5
